setup.py
funniesty/__init__.py
funniesty/text.py
funniesty.egg-info/PKG-INFO
funniesty.egg-info/SOURCES.txt
funniesty.egg-info/dependency_links.txt
funniesty.egg-info/not-zip-safe
funniesty.egg-info/requires.txt
funniesty.egg-info/top_level.txt