Metadata-Version: 1.0
Name: funniesty
Version: 0.2
Summary: The funniest joke in the world. NOT SO MUCH
Home-page: http://www.stangggtestsite/wp
Author: Flying Circus
Author-email: flyingcircus@example.com
License: MIT
Platform: UNKNOWN
